sklearn_migrator/__init__.py
sklearn_migrator/classification/__init__.py
sklearn_migrator/classification/decision_tree_clf.py
sklearn_migrator/classification/gradient_boosting_clf.py
sklearn_migrator/classification/knn_clf.py
sklearn_migrator/classification/logistic_regression_clf.py
sklearn_migrator/classification/mlp_clf.py
sklearn_migrator/classification/random_forest_clf.py
sklearn_migrator/classification/svm_clf.py
sklearn_migrator/clustering/__init__.py
sklearn_migrator/clustering/agglomerative.py
sklearn_migrator/clustering/k_means.py
sklearn_migrator/clustering/mini_batch_k_means.py
sklearn_migrator/dimension/__init__.py
sklearn_migrator/dimension/pca.py
sklearn_migrator/regression/__init__.py
sklearn_migrator/regression/adaboost_reg.py
sklearn_migrator/regression/decision_tree_reg.py
sklearn_migrator/regression/gradient_boosting_reg.py
sklearn_migrator/regression/knn_reg.py
sklearn_migrator/regression/lasso_reg.py
sklearn_migrator/regression/linear_regression_reg.py
sklearn_migrator/regression/mlp_reg.py
sklearn_migrator/regression/random_forest_reg.py
sklearn_migrator/regression/ridge_reg.py
sklearn_migrator/regression/svm_reg.py
sklearn_migrator-0.21.1.dist-info/licenses/LICENSE
sklearn_migrator-0.21.1.dist-info/METADATA
sklearn_migrator-0.21.1.dist-info/WHEEL
sklearn_migrator-0.21.1.dist-info/top_level.txt
sklearn_migrator-0.21.1.dist-info/RECORD
