Metadata-Version: 2.4
Name: sklearn-migrator
Version: 0.21.1
Summary: A utility to migrate scikit-learn models between versions.
Home-page: https://github.com/anvaldes/sklearn-migrator
Author: Alberto Valdés
Author-email: alberto.valdes.gonzalez.96.2@gmail.com
Project-URL: Documentation, https://github.com/anvaldes/sklearn-migrator#readme
Project-URL: Source, https://github.com/anvaldes/sklearn-migrator
Classifier: Programming Language :: Python :: 3
Classifier: License :: OSI Approved :: MIT License
Classifier: Operating System :: OS Independent
Requires-Python: >=3.8
License-File: LICENSE
Requires-Dist: scikit-learn>=0.21.3
Dynamic: author
Dynamic: author-email
Dynamic: classifier
Dynamic: description
Dynamic: description-content-type
Dynamic: home-page
Dynamic: license-file
Dynamic: project-url
Dynamic: requires-dist
Dynamic: requires-python
Dynamic: summary
